aiida_pyscf/__init__.py
aiida_pyscf/calculations/__init__.py
aiida_pyscf/calculations/base.py
aiida_pyscf/calculations/templates/cubegen.py.j2
aiida_pyscf/calculations/templates/fcidump.py.j2
aiida_pyscf/calculations/templates/geometric_log.ini
aiida_pyscf/calculations/templates/hessian.py.j2
aiida_pyscf/calculations/templates/mean_field.py.j2
aiida_pyscf/calculations/templates/optimizer.py.j2
aiida_pyscf/calculations/templates/results.py.j2
aiida_pyscf/calculations/templates/script.py.j2
aiida_pyscf/calculations/templates/structure.py.j2
aiida_pyscf/parsers/__init__.py
aiida_pyscf/parsers/base.py
aiida_pyscf/workflows/__init__.py
aiida_pyscf/workflows/base.py
aiida_pyscf-0.5.1.dist-info/entry_points.txt
aiida_pyscf-0.5.1.dist-info/LICENSE.txt
aiida_pyscf-0.5.1.dist-info/WHEEL
aiida_pyscf-0.5.1.dist-info/METADATA
aiida_pyscf-0.5.1.dist-info/RECORD
