Metadata-Version: 2.1
Name: aiida-pyscf
Version: 0.5.1
Summary: AiiDA plugin for the Python-based Simulations of Chemistry Framework (PySCF).
Keywords: aiida,workflows,pyscf
Author-email: "Sebastiaan P. Huber" <mail@sphuber.net>, Adam Grofe <v-adamgrofe@microsoft.com>
Requires-Python: >=3.9
Classifier: Development Status :: 3 - Alpha
Classifier: Framework :: AiiDA
Classifier: License :: OSI Approved :: MIT License
Classifier: Operating System :: POSIX :: Linux
Classifier: Operating System :: MacOS :: MacOS X
Classifier: Programming Language :: Python
Classifier: Programming Language :: Python :: 3.9
Classifier: Programming Language :: Python :: 3.10
Classifier: Programming Language :: Python :: 3.11
Classifier: Topic :: Scientific/Engineering
Requires-Dist: aiida-core[atomic_tools]~=2.5
Requires-Dist: aiida-shell>=0.5.3
Requires-Dist: dill
Requires-Dist: numpy
Requires-Dist: pint
Requires-Dist: pyscf[geomopt]~=2.2,<2.4
Requires-Dist: mypy==1.8.0 ; extra == "pre-commit"
Requires-Dist: pre-commit~=2.17 ; extra == "pre-commit"
Requires-Dist: packaging ; extra == "tests"
Requires-Dist: pgtest~=1.3,>=1.3.1 ; extra == "tests"
Requires-Dist: pytest~=7.2 ; extra == "tests"
Requires-Dist: pytest-regressions ; extra == "tests"
Project-URL: Source, https://github.com/microsoft/aiida-pyscf
Provides-Extra: pre-commit
Provides-Extra: tests
